LICENSE.TXT
README.md
setup.cfg
setup.py
src/__pycache__/__init__.cpython-37.pyc
src/__pycache__/clock_keeper.cpython-37.pyc
src/__pycache__/clockkeeper.cpython-37.pyc
src/clock_keeper/__init__.py
src/clock_keeper/utility.py
src/clock_keeper.egg-info/PKG-INFO
src/clock_keeper.egg-info/SOURCES.txt
src/clock_keeper.egg-info/dependency_links.txt
src/clock_keeper.egg-info/top_level.txt
src/clock_keeper/example/__init__.py
src/clock_keeper/example/usage.py
tests/__init__.py
tests/clock_keeper/example/__init__.py