Metadata-Version: 2.1
Name: clock-keeper
Version: 0.7.6
Summary: A very minimalistic python module that lets you track the time your code snippets take to run.
Home-page: https://github.com/rajdeep-biswas/clock-keeper
Author: Rajdeep Biswas
Author-email: r4jdeepbiswas@gmail.com
License: MIT
Project-URL: Source, https://github.com/rajdeep-biswas/clock-keeper
Project-URL: Say Thanks!, http://linkedin.com/in/rajdeep-biswas
Keywords: clock keeper timer stop watch
Platform: UNKNOWN
